<?xml version="1.0" encoding="utf-8" ?>
<RegMap>
  <!--Group-->
  <!--Custom,Digital,SPI,Analog,MIPIDig,MIPIAna,Efuse,-->
  <!--<Custom>
    
  </Custom>-->
  <Digital>
    <Reg Name="Sequencer_Go">
      <Address>0x0400</Address>
      <RegVal>0x00000000</RegVal>
      <IsRealTime>true</IsRealTime>
      <IsWriteable>true</IsWriteable>
      <IsReadable>true</IsReadable>
      <Ranges>
      </Ranges>
    </Reg>
    <Reg Name="Reg_Hold">
      <Address>0x0401</Address>
      <RegVal>0x00000000</RegVal>
      <IsRealTime>true</IsRealTime>
      <IsWriteable>true</IsWriteable>
      <IsReadable>true</IsReadable>
      <Ranges>
        <Range>
          <Start>1</Start>
          <End>31</End>
          <Min>0</Min>
          <Max>0</Max>
        </Range>
      </Ranges>
    </Reg>
    <Reg Name="Glb_Cfg_Reg0">
      <Address>0x0402</Address>
      <RegVal>0x0040081b</RegVal>
      <IsRealTime>false</IsRealTime>
      <IsWriteable>true</IsWriteable>
      <IsReadable>true</IsReadable>
      <Ranges>
        <Range>
          <Start>15</Start>
          <End>17</End>
          <Min>0</Min>
          <Max>0</Max>
        </Range>
      </Ranges>
    </Reg>
    <Reg Name="Tsensor_Value0">
      <Address>0x0407</Address>
      <RegVal>0x00000000</RegVal>
      <IsRealTime>true</IsRealTime>
      <IsWriteable>false</IsWriteable>
      <IsReadable>true</IsReadable>
      <Ranges>
        <Range>
          <Start>1</Start>
          <End>7</End>
          <Min>0</Min>
          <Max>0</Max>
        </Range>
      </Ranges>
    </Reg>
    <Reg Name="Dll_Cfg_Reg">
      <Address>0x0408</Address>
      <RegVal>0x80000055</RegVal>
      <IsRealTime>true</IsRealTime>
      <IsWriteable>true</IsWriteable>
      <IsReadable>true</IsReadable>
      <Ranges>
        <Range>
          <Start>10</Start>
          <End>15</End>
          <Min>0</Min>
          <Max>0</Max>
        </Range>
      </Ranges>
    </Reg>
    <Reg Name="Frame_Rate">
      <Address>0x0429</Address>
      <RegVal>0x000186a0</RegVal>
      <IsRealTime>true</IsRealTime>
      <IsWriteable>true</IsWriteable>
      <IsReadable>true</IsReadable>
      <Ranges>
      </Ranges>
    </Reg>
    <Reg Name="Burst_Mode_Cfg">
      <Address>0x0430</Address>
      <RegVal>0x02000000</RegVal>
      <IsRealTime>true</IsRealTime>
      <IsWriteable>true</IsWriteable>
      <IsReadable>true</IsReadable>
      <Ranges>
        <Range>
          <Start>24</Start>
          <End>24</End>
          <Min>0</Min>
          <Max>0</Max>
        </Range>
        <Range>
          <Start>27</Start>
          <End>30</End>
          <Min>0</Min>
          <Max>0</Max>
        </Range>
      </Ranges>
    </Reg>
    <Reg Name="Matrix_Cfg0">
      <Address>0x0431</Address>
      <RegVal>0x04042220</RegVal>
      <IsRealTime>true</IsRealTime>
      <IsWriteable>true</IsWriteable>
      <IsReadable>true</IsReadable>
      <Ranges>
        <Range>
          <Start>11</Start>
          <End>11</End>
          <Min>0</Min>
          <Max>0</Max>
        </Range>
        <Range>
          <Start>15</Start>
          <End>15</End>
          <Min>0</Min>
          <Max>0</Max>
        </Range>
        <Range>
          <Start>23</Start>
          <End>23</End>
          <Min>0</Min>
          <Max>0</Max>
        </Range>
        <Range>
          <Start>31</Start>
          <End>31</End>
          <Min>0</Min>
          <Max>0</Max>
        </Range>
      </Ranges>
    </Reg>
    <Reg Name="Matrix_Cfg1">
      <Address>0x0432</Address>
      <RegVal>0x0d192626</RegVal>
      <IsRealTime>true</IsRealTime>
      <IsWriteable>true</IsWriteable>
      <IsReadable>true</IsReadable>
      <Ranges>
        <Range>
          <Start>6</Start>
          <End>7</End>
          <Min>0</Min>
          <Max>0</Max>
        </Range>
        <Range>
          <Start>14</Start>
          <End>15</End>
          <Min>0</Min>
          <Max>0</Max>
        </Range>
        <Range>
          <Start>22</Start>
          <End>23</End>
          <Min>0</Min>
          <Max>0</Max>
        </Range>
        <Range>
          <Start>30</Start>
          <End>30</End>
          <Min>0</Min>
          <Max>0</Max>
        </Range>
      </Ranges>
    </Reg>
    <Reg Name="Matrix_Cfg2">
      <Address>0x0433</Address>
      <RegVal>0x014521f4</RegVal>
      <IsRealTime>true</IsRealTime>
      <IsWriteable>true</IsWriteable>
      <IsReadable>true</IsReadable>
      <Ranges>
        <Range>
          <Start>15</Start>
          <End>15</End>
          <Min>0</Min>
          <Max>0</Max>
        </Range>
        <Range>
          <Start>28</Start>
          <End>31</End>
          <Min>0</Min>
          <Max>0</Max>
        </Range>
      </Ranges>
    </Reg>
    <Reg Name="Matrix_Cfg3">
      <Address>0x0434</Address>
      <RegVal>0x11190020</RegVal>
      <IsRealTime>true</IsRealTime>
      <IsWriteable>true</IsWriteable>
      <IsReadable>true</IsReadable>
      <Ranges>
        <Range>
          <Start>14</Start>
          <End>15</End>
          <Min>0</Min>
          <Max>0</Max>
        </Range>
      </Ranges>
    </Reg>
    <Reg Name="Matrix_Cfg4">
      <Address>0x0435</Address>
      <RegVal>0x0000000d</RegVal>
      <IsRealTime>true</IsRealTime>
      <IsWriteable>true</IsWriteable>
      <IsReadable>true</IsReadable>
      <Ranges>
      </Ranges>
    </Reg>
    <Reg Name="Apc_Cfg">
      <Address>0x0436</Address>
      <RegVal>0x00000002</RegVal>
      <IsRealTime>true</IsRealTime>
      <IsWriteable>true</IsWriteable>
      <IsReadable>true</IsReadable>
      <Ranges>
        <Range>
          <Start>2</Start>
          <End>3</End>
          <Min>0</Min>
          <Max>0</Max>
        </Range>
        <Range>
          <Start>16</Start>
          <End>27</End>
          <Min>0</Min>
          <Max>0</Max>
        </Range>
        <Range>
          <Start>30</Start>
          <End>30</End>
          <Min>0</Min>
          <Max>0</Max>
        </Range>
      </Ranges>
    </Reg>
    <Reg Name="Adc_Cali_Ctrl">
      <Address>0x0437</Address>
      <RegVal>0x04285602</RegVal>
      <IsRealTime>true</IsRealTime>
      <IsWriteable>true</IsWriteable>
      <IsReadable>true</IsReadable>
      <Ranges>
      </Ranges>
    </Reg>
    <Reg Name="Adc_Cali_Cnt">
      <Address>0x0438</Address>
      <RegVal>0x0001e87d</RegVal>
      <IsRealTime>true</IsRealTime>
      <IsWriteable>true</IsWriteable>
      <IsReadable>true</IsReadable>
      <Ranges>
      </Ranges>
    </Reg>
    <Reg Name="Adc_Cali0">
      <Address>0x0440</Address>
      <RegVal>0x00000000</RegVal>
      <IsRealTime>true</IsRealTime>
      <IsWriteable>false</IsWriteable>
      <IsReadable>true</IsReadable>
      <Ranges>
      </Ranges>
    </Reg>
    <Reg Name="Adc_Cali1">
      <Address>0x0441</Address>
      <RegVal>0x00000000</RegVal>
      <IsRealTime>true</IsRealTime>
      <IsWriteable>false</IsWriteable>
      <IsReadable>true</IsReadable>
      <Ranges>
      </Ranges>
    </Reg>
    <Reg Name="Adc_Cali2">
      <Address>0x0442</Address>
      <RegVal>0x00000000</RegVal>
      <IsRealTime>true</IsRealTime>
      <IsWriteable>false</IsWriteable>
      <IsReadable>true</IsReadable>
      <Ranges>
      </Ranges>
    </Reg>
    <Reg Name="Adc_Cali3">
      <Address>0x0443</Address>
      <RegVal>0x00000000</RegVal>
      <IsRealTime>true</IsRealTime>
      <IsWriteable>false</IsWriteable>
      <IsReadable>true</IsReadable>
      <Ranges>
      </Ranges>
    </Reg>
    <Reg Name="Adc_Cali4">
      <Address>0x0444</Address>
      <RegVal>0x00000000</RegVal>
      <IsRealTime>true</IsRealTime>
      <IsWriteable>false</IsWriteable>
      <IsReadable>true</IsReadable>
      <Ranges>
      </Ranges>
    </Reg>
    <Reg Name="Adc_Cali5">
      <Address>0x0445</Address>
      <RegVal>0x00000000</RegVal>
      <IsRealTime>true</IsRealTime>
      <IsWriteable>false</IsWriteable>
      <IsReadable>true</IsReadable>
      <Ranges>
      </Ranges>
    </Reg>
    <Reg Name="Adc_Cali6">
      <Address>0x0446</Address>
      <RegVal>0x00000000</RegVal>
      <IsRealTime>true</IsRealTime>
      <IsWriteable>false</IsWriteable>
      <IsReadable>true</IsReadable>
      <Ranges>
      </Ranges>
    </Reg>
    <Reg Name="Adc_Cali7">
      <Address>0x0447</Address>
      <RegVal>0x00000000</RegVal>
      <IsRealTime>true</IsRealTime>
      <IsWriteable>false</IsWriteable>
      <IsReadable>true</IsReadable>
      <Ranges>
      </Ranges>
    </Reg>
    <Reg Name="Adc_Cali8">
      <Address>0x0448</Address>
      <RegVal>0x00000000</RegVal>
      <IsRealTime>true</IsRealTime>
      <IsWriteable>false</IsWriteable>
      <IsReadable>true</IsReadable>
      <Ranges>
      </Ranges>
    </Reg>
    <Reg Name="Adc_Cali9">
      <Address>0x0449</Address>
      <RegVal>0x00000000</RegVal>
      <IsRealTime>true</IsRealTime>
      <IsWriteable>false</IsWriteable>
      <IsReadable>true</IsReadable>
      <Ranges>
      </Ranges>
    </Reg>
    <Reg Name="Adc_Calia">
      <Address>0x044a</Address>
      <RegVal>0x00000000</RegVal>
      <IsRealTime>true</IsRealTime>
      <IsWriteable>false</IsWriteable>
      <IsReadable>true</IsReadable>
      <Ranges>
      </Ranges>
    </Reg>
    <Reg Name="Adc_Calib">
      <Address>0x044b</Address>
      <RegVal>0x00000000</RegVal>
      <IsRealTime>true</IsRealTime>
      <IsWriteable>false</IsWriteable>
      <IsReadable>true</IsReadable>
      <Ranges>
      </Ranges>
    </Reg>
    <Reg Name="Adc_Calic">
      <Address>0x044c</Address>
      <RegVal>0x00000000</RegVal>
      <IsRealTime>true</IsRealTime>
      <IsWriteable>false</IsWriteable>
      <IsReadable>true</IsReadable>
      <Ranges>
      </Ranges>
    </Reg>
    <Reg Name="Adc_Calid">
      <Address>0x044d</Address>
      <RegVal>0x00000000</RegVal>
      <IsRealTime>true</IsRealTime>
      <IsWriteable>false</IsWriteable>
      <IsReadable>true</IsReadable>
      <Ranges>
      </Ranges>
    </Reg>
    <Reg Name="Adc_Calie">
      <Address>0x044e</Address>
      <RegVal>0x00000000</RegVal>
      <IsRealTime>true</IsRealTime>
      <IsWriteable>false</IsWriteable>
      <IsReadable>true</IsReadable>
      <Ranges>
      </Ranges>
    </Reg>
    <Reg Name="Adc_Calif">
      <Address>0x044f</Address>
      <RegVal>0x00000000</RegVal>
      <IsRealTime>true</IsRealTime>
      <IsWriteable>false</IsWriteable>
      <IsReadable>true</IsReadable>
      <Ranges>
      </Ranges>
    </Reg>
    <Reg Name="Seq_Glb_Cfg0">
      <Address>0x0470</Address>
      <RegVal>0x00000008</RegVal>
      <IsRealTime>true</IsRealTime>
      <IsWriteable>true</IsWriteable>
      <IsReadable>true</IsReadable>
      <Ranges>
        <Range>
          <Start>19</Start>
          <End>19</End>
          <Min>0</Min>
          <Max>0</Max>
        </Range>
        <Range>
          <Start>23</Start>
          <End>23</End>
          <Min>0</Min>
          <Max>0</Max>
        </Range>
        <Range>
          <Start>27</Start>
          <End>27</End>
          <Min>0</Min>
          <Max>0</Max>
        </Range>
        <Range>
          <Start>31</Start>
          <End>31</End>
          <Min>0</Min>
          <Max>0</Max>
        </Range>
      </Ranges>
    </Reg>
    <Reg Name="Seq_Glb_Cfg1">
      <Address>0x0471</Address>
      <RegVal>0x00010001</RegVal>
      <IsRealTime>true</IsRealTime>
      <IsWriteable>true</IsWriteable>
      <IsReadable>true</IsReadable>
      <Ranges>
      </Ranges>
    </Reg>
    <Reg Name="Seq_Glb_Cfg2">
      <Address>0x0472</Address>
      <RegVal>0x00010001</RegVal>
      <IsRealTime>true</IsRealTime>
      <IsWriteable>true</IsWriteable>
      <IsReadable>true</IsReadable>
      <Ranges>
      </Ranges>
    </Reg>
    <Reg Name="Roi_Ctrlx">
      <Address>0x0473</Address>
      <RegVal>0x001a0000</RegVal>
      <IsRealTime>false</IsRealTime>
      <IsWriteable>true</IsWriteable>
      <IsReadable>true</IsReadable>
      <Ranges>
        <Range>
          <Start>10</Start>
          <End>11</End>
          <Min>0</Min>
          <Max>0</Max>
        </Range>
        <Range>
          <Start>25</Start>
          <End>31</End>
          <Min>0</Min>
          <Max>0</Max>
        </Range>
      </Ranges>
    </Reg>
    <Reg Name="Roi_Ctrly">
      <Address>0x0474</Address>
      <RegVal>0x00178000</RegVal>
      <IsRealTime>false</IsRealTime>
      <IsWriteable>true</IsWriteable>
      <IsReadable>true</IsReadable>
      <Ranges>
        <Range>
          <Start>9</Start>
          <End>9</End>
          <Min>0</Min>
          <Max>0</Max>
        </Range>
        <Range>
          <Start>19</Start>
          <End>19</End>
          <Min>0</Min>
          <Max>0</Max>
        </Range>
        <Range>
          <Start>25</Start>
          <End>31</End>
          <Min>0</Min>
          <Max>0</Max>
        </Range>
      </Ranges>
    </Reg>
    <Reg Name="Subframe_Idle">
      <Address>0x0475</Address>
      <RegVal>0x00000064</RegVal>
      <IsRealTime>true</IsRealTime>
      <IsWriteable>true</IsWriteable>
      <IsReadable>true</IsReadable>
      <Ranges>
      </Ranges>
    </Reg>
    <Reg Name="Frame_Idle">
      <Address>0x0476</Address>
      <RegVal>0x000003e8</RegVal>
      <IsRealTime>true</IsRealTime>
      <IsWriteable>true</IsWriteable>
      <IsReadable>true</IsReadable>
      <Ranges>
      </Ranges>
    </Reg>
    <Reg Name="Int_Ctrl">
      <Address>0x0477</Address>
      <RegVal>0x00000000</RegVal>
      <IsRealTime>true</IsRealTime>
      <IsWriteable>true</IsWriteable>
      <IsReadable>true</IsReadable>
      <Ranges>
        <Range>
          <Start>4</Start>
          <End>31</End>
          <Min>0</Min>
          <Max>0</Max>
        </Range>
      </Ranges>
    </Reg>
    <Reg Name="Seq0_Set0">
      <Address>0x0480</Address>
      <RegVal>0x009603e8</RegVal>
      <IsRealTime>true</IsRealTime>
      <IsWriteable>true</IsWriteable>
      <IsReadable>true</IsReadable>
      <Ranges>
        <Range>
          <Start>27</Start>
          <End>31</End>
          <Min>0</Min>
          <Max>0</Max>
        </Range>
      </Ranges>
    </Reg>
    <Reg Name="Seq0_Set1">
      <Address>0x0481</Address>
      <RegVal>0x009603e8</RegVal>
      <IsRealTime>true</IsRealTime>
      <IsWriteable>true</IsWriteable>
      <IsReadable>true</IsReadable>
      <Ranges>
        <Range>
          <Start>27</Start>
          <End>31</End>
          <Min>0</Min>
          <Max>0</Max>
        </Range>
      </Ranges>
    </Reg>
    <Reg Name="Seq0_Set2">
      <Address>0x0482</Address>
      <RegVal>0x00184100</RegVal>
      <IsRealTime>true</IsRealTime>
      <IsWriteable>true</IsWriteable>
      <IsReadable>true</IsReadable>
      <Ranges>
        <Range>
          <Start>15</Start>
          <End>15</End>
          <Min>0</Min>
          <Max>0</Max>
        </Range>
        <Range>
          <Start>26</Start>
          <End>26</End>
          <Min>0</Min>
          <Max>0</Max>
        </Range>
      </Ranges>
    </Reg>
    <Reg Name="Seq0_Set3">
      <Address>0x0483</Address>
      <RegVal>0x00184100</RegVal>
      <IsRealTime>true</IsRealTime>
      <IsWriteable>true</IsWriteable>
      <IsReadable>true</IsReadable>
      <Ranges>
        <Range>
          <Start>15</Start>
          <End>15</End>
          <Min>0</Min>
          <Max>0</Max>
        </Range>
        <Range>
          <Start>26</Start>
          <End>26</End>
          <Min>0</Min>
          <Max>0</Max>
        </Range>
      </Ranges>
    </Reg>
    <Reg Name="Seq0_Set4">
      <Address>0x0484</Address>
      <RegVal>0x301603e8</RegVal>
      <IsRealTime>true</IsRealTime>
      <IsWriteable>true</IsWriteable>
      <IsReadable>true</IsReadable>
      <Ranges>
        <Range>
          <Start>23</Start>
          <End>23</End>
          <Min>0</Min>
          <Max>0</Max>
        </Range>
        <Range>
          <Start>30</Start>
          <End>31</End>
          <Min>0</Min>
          <Max>0</Max>
        </Range>
      </Ranges>
    </Reg>
    <Reg Name="Seq1_Set0">
      <Address>0x0485</Address>
      <RegVal>0x009603e8</RegVal>
      <IsRealTime>true</IsRealTime>
      <IsWriteable>true</IsWriteable>
      <IsReadable>true</IsReadable>
      <Ranges>
        <Range>
          <Start>27</Start>
          <End>31</End>
          <Min>0</Min>
          <Max>0</Max>
        </Range>
      </Ranges>
    </Reg>
    <Reg Name="Seq1_Set1">
      <Address>0x0486</Address>
      <RegVal>0x009603e8</RegVal>
      <IsRealTime>true</IsRealTime>
      <IsWriteable>true</IsWriteable>
      <IsReadable>true</IsReadable>
      <Ranges>
        <Range>
          <Start>27</Start>
          <End>31</End>
          <Min>0</Min>
          <Max>0</Max>
        </Range>
      </Ranges>
    </Reg>
    <Reg Name="Seq1_Set2">
      <Address>0x0487</Address>
      <RegVal>0x00184100</RegVal>
      <IsRealTime>true</IsRealTime>
      <IsWriteable>true</IsWriteable>
      <IsReadable>true</IsReadable>
      <Ranges>
        <Range>
          <Start>15</Start>
          <End>15</End>
          <Min>0</Min>
          <Max>0</Max>
        </Range>
        <Range>
          <Start>26</Start>
          <End>26</End>
          <Min>0</Min>
          <Max>0</Max>
        </Range>
      </Ranges>
    </Reg>
    <Reg Name="Seq1_Set3">
      <Address>0x0488</Address>
      <RegVal>0x00184100</RegVal>
      <IsRealTime>true</IsRealTime>
      <IsWriteable>true</IsWriteable>
      <IsReadable>true</IsReadable>
      <Ranges>
        <Range>
          <Start>15</Start>
          <End>15</End>
          <Min>0</Min>
          <Max>0</Max>
        </Range>
        <Range>
          <Start>26</Start>
          <End>26</End>
          <Min>0</Min>
          <Max>0</Max>
        </Range>
      </Ranges>
    </Reg>
    <Reg Name="Seq1_Set4">
      <Address>0x0489</Address>
      <RegVal>0x301603e8</RegVal>
      <IsRealTime>true</IsRealTime>
      <IsWriteable>true</IsWriteable>
      <IsReadable>true</IsReadable>
      <Ranges>
        <Range>
          <Start>23</Start>
          <End>23</End>
          <Min>0</Min>
          <Max>0</Max>
        </Range>
        <Range>
          <Start>30</Start>
          <End>31</End>
          <Min>0</Min>
          <Max>0</Max>
        </Range>
      </Ranges>
    </Reg>
    <Reg Name="Seq2_Set0">
      <Address>0x048a</Address>
      <RegVal>0x009603e8</RegVal>
      <IsRealTime>true</IsRealTime>
      <IsWriteable>true</IsWriteable>
      <IsReadable>true</IsReadable>
      <Ranges>
        <Range>
          <Start>27</Start>
          <End>31</End>
          <Min>0</Min>
          <Max>0</Max>
        </Range>
      </Ranges>
    </Reg>
    <Reg Name="Seq2_Set1">
      <Address>0x048b</Address>
      <RegVal>0x009603e8</RegVal>
      <IsRealTime>true</IsRealTime>
      <IsWriteable>true</IsWriteable>
      <IsReadable>true</IsReadable>
      <Ranges>
        <Range>
          <Start>27</Start>
          <End>31</End>
          <Min>0</Min>
          <Max>0</Max>
        </Range>
      </Ranges>
    </Reg>
    <Reg Name="Seq2_Set2">
      <Address>0x048c</Address>
      <RegVal>0x00184100</RegVal>
      <IsRealTime>true</IsRealTime>
      <IsWriteable>true</IsWriteable>
      <IsReadable>true</IsReadable>
      <Ranges>
        <Range>
          <Start>15</Start>
          <End>15</End>
          <Min>0</Min>
          <Max>0</Max>
        </Range>
        <Range>
          <Start>26</Start>
          <End>26</End>
          <Min>0</Min>
          <Max>0</Max>
        </Range>
      </Ranges>
    </Reg>
    <Reg Name="Seq2_Set3">
      <Address>0x048d</Address>
      <RegVal>0x00184100</RegVal>
      <IsRealTime>true</IsRealTime>
      <IsWriteable>true</IsWriteable>
      <IsReadable>true</IsReadable>
      <Ranges>
        <Range>
          <Start>15</Start>
          <End>15</End>
          <Min>0</Min>
          <Max>0</Max>
        </Range>
        <Range>
          <Start>26</Start>
          <End>26</End>
          <Min>0</Min>
          <Max>0</Max>
        </Range>
      </Ranges>
    </Reg>
    <Reg Name="Seq2_Set4">
      <Address>0x048e</Address>
      <RegVal>0x301603e8</RegVal>
      <IsRealTime>true</IsRealTime>
      <IsWriteable>true</IsWriteable>
      <IsReadable>true</IsReadable>
      <Ranges>
        <Range>
          <Start>23</Start>
          <End>23</End>
          <Min>0</Min>
          <Max>0</Max>
        </Range>
        <Range>
          <Start>30</Start>
          <End>31</End>
          <Min>0</Min>
          <Max>0</Max>
        </Range>
      </Ranges>
    </Reg>
    <Reg Name="Seq3_Set0">
      <Address>0x048f</Address>
      <RegVal>0x009603e8</RegVal>
      <IsRealTime>true</IsRealTime>
      <IsWriteable>true</IsWriteable>
      <IsReadable>true</IsReadable>
      <Ranges>
        <Range>
          <Start>27</Start>
          <End>31</End>
          <Min>0</Min>
          <Max>0</Max>
        </Range>
      </Ranges>
    </Reg>
    <Reg Name="Seq3_Set1">
      <Address>0x0490</Address>
      <RegVal>0x009603e8</RegVal>
      <IsRealTime>true</IsRealTime>
      <IsWriteable>true</IsWriteable>
      <IsReadable>true</IsReadable>
      <Ranges>
        <Range>
          <Start>27</Start>
          <End>31</End>
          <Min>0</Min>
          <Max>0</Max>
        </Range>
      </Ranges>
    </Reg>
    <Reg Name="Seq3_Set2">
      <Address>0x0491</Address>
      <RegVal>0x00184100</RegVal>
      <IsRealTime>true</IsRealTime>
      <IsWriteable>true</IsWriteable>
      <IsReadable>true</IsReadable>
      <Ranges>
        <Range>
          <Start>15</Start>
          <End>15</End>
          <Min>0</Min>
          <Max>0</Max>
        </Range>
        <Range>
          <Start>26</Start>
          <End>26</End>
          <Min>0</Min>
          <Max>0</Max>
        </Range>
      </Ranges>
    </Reg>
    <Reg Name="Seq3_Set3">
      <Address>0x0492</Address>
      <RegVal>0x00184100</RegVal>
      <IsRealTime>true</IsRealTime>
      <IsWriteable>true</IsWriteable>
      <IsReadable>true</IsReadable>
      <Ranges>
        <Range>
          <Start>15</Start>
          <End>15</End>
          <Min>0</Min>
          <Max>0</Max>
        </Range>
        <Range>
          <Start>26</Start>
          <End>26</End>
          <Min>0</Min>
          <Max>0</Max>
        </Range>
      </Ranges>
    </Reg>
    <Reg Name="Seq3_Set4">
      <Address>0x0493</Address>
      <RegVal>0x301603e8</RegVal>
      <IsRealTime>true</IsRealTime>
      <IsWriteable>true</IsWriteable>
      <IsReadable>true</IsReadable>
      <Ranges>
        <Range>
          <Start>23</Start>
          <End>23</End>
          <Min>0</Min>
          <Max>0</Max>
        </Range>
        <Range>
          <Start>30</Start>
          <End>31</End>
          <Min>0</Min>
          <Max>0</Max>
        </Range>
      </Ranges>
    </Reg>
    <Reg Name="Bist_Cfg0">
      <Address>0x04a0</Address>
      <RegVal>0x00000000</RegVal>
      <IsRealTime>true</IsRealTime>
      <IsWriteable>true</IsWriteable>
      <IsReadable>true</IsReadable>
      <Ranges>
        <Range>
          <Start>0</Start>
          <End>2</End>
          <Min>0</Min>
          <Max>0</Max>
        </Range>
        <Range>
          <Start>8</Start>
          <End>31</End>
          <Min>0</Min>
          <Max>0</Max>
        </Range>
      </Ranges>
    </Reg>
    <Reg Name="Mipi_Cfg">
      <Address>0x04a3</Address>
      <RegVal>0x00000010</RegVal>
      <IsRealTime>true</IsRealTime>
      <IsWriteable>true</IsWriteable>
      <IsReadable>true</IsReadable>
      <Ranges>
        <Range>
          <Start>17</Start>
          <End>31</End>
          <Min>0</Min>
          <Max>0</Max>
        </Range>
      </Ranges>
    </Reg>
    <Reg Name="Sw_Id0">
      <Address>0x04fe</Address>
      <RegVal>0x00000000</RegVal>
      <IsRealTime>true</IsRealTime>
      <IsWriteable>true</IsWriteable>
      <IsReadable>true</IsReadable>
      <Ranges>
      </Ranges>
    </Reg>
    <Reg Name="Sw_Id1">
      <Address>0x04ff</Address>
      <RegVal>0x00000000</RegVal>
      <IsRealTime>true</IsRealTime>
      <IsWriteable>true</IsWriteable>
      <IsReadable>true</IsReadable>
      <Ranges>
      </Ranges>
    </Reg>
    
  </Digital>
  <SPI>
    <Reg Name="Spi_Trans_Buf0">
      <Address>0x0700</Address>
      <RegVal>0x00000000</RegVal>
      <IsRealTime>true</IsRealTime>
      <IsWriteable>true</IsWriteable>
      <IsReadable>true</IsReadable>
      <Ranges>
      </Ranges>
    </Reg>
    <Reg Name="Spi_Trans_Buf1">
      <Address>0x0701</Address>
      <RegVal>0x00000000</RegVal>
      <IsRealTime>true</IsRealTime>
      <IsWriteable>true</IsWriteable>
      <IsReadable>true</IsReadable>
      <Ranges>
      </Ranges>
    </Reg>
    <Reg Name="Spi_Trans_Buf2">
      <Address>0x0702</Address>
      <RegVal>0x00000000</RegVal>
      <IsRealTime>true</IsRealTime>
      <IsWriteable>true</IsWriteable>
      <IsReadable>true</IsReadable>
      <Ranges>
      </Ranges>
    </Reg>
    <Reg Name="Spi_Trans_Buf3">
      <Address>0x0703</Address>
      <RegVal>0x00000000</RegVal>
      <IsRealTime>true</IsRealTime>
      <IsWriteable>true</IsWriteable>
      <IsReadable>true</IsReadable>
      <Ranges>
      </Ranges>
    </Reg>
    <Reg Name="Spi_Trans_Buf4">
      <Address>0x0704</Address>
      <RegVal>0x00000000</RegVal>
      <IsRealTime>true</IsRealTime>
      <IsWriteable>true</IsWriteable>
      <IsReadable>true</IsReadable>
      <Ranges>
      </Ranges>
    </Reg>
    <Reg Name="Spi_Trans_Buf5">
      <Address>0x0705</Address>
      <RegVal>0x00000000</RegVal>
      <IsRealTime>true</IsRealTime>
      <IsWriteable>true</IsWriteable>
      <IsReadable>true</IsReadable>
      <Ranges>
      </Ranges>
    </Reg>
    <Reg Name="Spi_Trans_Buf6">
      <Address>0x0706</Address>
      <RegVal>0x00000000</RegVal>
      <IsRealTime>true</IsRealTime>
      <IsWriteable>true</IsWriteable>
      <IsReadable>true</IsReadable>
      <Ranges>
      </Ranges>
    </Reg>
    <Reg Name="Spi_Trans_Buf7">
      <Address>0x0707</Address>
      <RegVal>0x00000000</RegVal>
      <IsRealTime>true</IsRealTime>
      <IsWriteable>true</IsWriteable>
      <IsReadable>true</IsReadable>
      <Ranges>
      </Ranges>
    </Reg>
    <Reg Name="Spi_Trans_Buf8">
      <Address>0x0708</Address>
      <RegVal>0x00000000</RegVal>
      <IsRealTime>true</IsRealTime>
      <IsWriteable>true</IsWriteable>
      <IsReadable>true</IsReadable>
      <Ranges>
      </Ranges>
    </Reg>
    <Reg Name="Spi_Trans_Buf9">
      <Address>0x0709</Address>
      <RegVal>0x00000000</RegVal>
      <IsRealTime>true</IsRealTime>
      <IsWriteable>true</IsWriteable>
      <IsReadable>true</IsReadable>
      <Ranges>
      </Ranges>
    </Reg>
    <Reg Name="Spi_Trans_Bufa">
      <Address>0x070a</Address>
      <RegVal>0x00000000</RegVal>
      <IsRealTime>true</IsRealTime>
      <IsWriteable>true</IsWriteable>
      <IsReadable>true</IsReadable>
      <Ranges>
      </Ranges>
    </Reg>
    <Reg Name="Spi_Trans_Bufb">
      <Address>0x070b</Address>
      <RegVal>0x00000000</RegVal>
      <IsRealTime>true</IsRealTime>
      <IsWriteable>true</IsWriteable>
      <IsReadable>true</IsReadable>
      <Ranges>
      </Ranges>
    </Reg>
    <Reg Name="Spi_Trans_Bufc">
      <Address>0x070c</Address>
      <RegVal>0x00000000</RegVal>
      <IsRealTime>true</IsRealTime>
      <IsWriteable>true</IsWriteable>
      <IsReadable>true</IsReadable>
      <Ranges>
      </Ranges>
    </Reg>
    <Reg Name="Spi_Trans_Bufd">
      <Address>0x070d</Address>
      <RegVal>0x00000000</RegVal>
      <IsRealTime>true</IsRealTime>
      <IsWriteable>true</IsWriteable>
      <IsReadable>true</IsReadable>
      <Ranges>
      </Ranges>
    </Reg>
    <Reg Name="Spi_Trans_Bufe">
      <Address>0x070e</Address>
      <RegVal>0x00000000</RegVal>
      <IsRealTime>true</IsRealTime>
      <IsWriteable>true</IsWriteable>
      <IsReadable>true</IsReadable>
      <Ranges>
      </Ranges>
    </Reg>
    <Reg Name="Spi_Trans_Buff">
      <Address>0x070f</Address>
      <RegVal>0x00000000</RegVal>
      <IsRealTime>true</IsRealTime>
      <IsWriteable>true</IsWriteable>
      <IsReadable>true</IsReadable>
      <Ranges>
      </Ranges>
    </Reg>
    <Reg Name="Spi_Receive_Buf0">
      <Address>0x0710</Address>
      <RegVal>0x00000000</RegVal>
      <IsRealTime>true</IsRealTime>
      <IsWriteable>true</IsWriteable>
      <IsReadable>true</IsReadable>
      <Ranges>
      </Ranges>
    </Reg>
    <Reg Name="Spi_Receive_Buf1">
      <Address>0x0711</Address>
      <RegVal>0x00000000</RegVal>
      <IsRealTime>true</IsRealTime>
      <IsWriteable>true</IsWriteable>
      <IsReadable>true</IsReadable>
      <Ranges>
      </Ranges>
    </Reg>
    <Reg Name="Spi_Receive_Buf2">
      <Address>0x0712</Address>
      <RegVal>0x00000000</RegVal>
      <IsRealTime>true</IsRealTime>
      <IsWriteable>true</IsWriteable>
      <IsReadable>true</IsReadable>
      <Ranges>
      </Ranges>
    </Reg>
    <Reg Name="Spi_Receive_Buf3">
      <Address>0x0713</Address>
      <RegVal>0x00000000</RegVal>
      <IsRealTime>true</IsRealTime>
      <IsWriteable>true</IsWriteable>
      <IsReadable>true</IsReadable>
      <Ranges>
      </Ranges>
    </Reg>
    <Reg Name="Spi_Receive_Buf4">
      <Address>0x0714</Address>
      <RegVal>0x00000000</RegVal>
      <IsRealTime>true</IsRealTime>
      <IsWriteable>true</IsWriteable>
      <IsReadable>true</IsReadable>
      <Ranges>
      </Ranges>
    </Reg>
    <Reg Name="Spi_Receive_Buf5">
      <Address>0x0715</Address>
      <RegVal>0x00000000</RegVal>
      <IsRealTime>true</IsRealTime>
      <IsWriteable>true</IsWriteable>
      <IsReadable>true</IsReadable>
      <Ranges>
      </Ranges>
    </Reg>
    <Reg Name="Spi_Receive_Buf6">
      <Address>0x0716</Address>
      <RegVal>0x00000000</RegVal>
      <IsRealTime>true</IsRealTime>
      <IsWriteable>true</IsWriteable>
      <IsReadable>true</IsReadable>
      <Ranges>
      </Ranges>
    </Reg>
    <Reg Name="Spi_Receive_Buf7">
      <Address>0x0717</Address>
      <RegVal>0x00000000</RegVal>
      <IsRealTime>true</IsRealTime>
      <IsWriteable>true</IsWriteable>
      <IsReadable>true</IsReadable>
      <Ranges>
      </Ranges>
    </Reg>
    <Reg Name="Spi_Receive_Buf8">
      <Address>0x0718</Address>
      <RegVal>0x00000000</RegVal>
      <IsRealTime>true</IsRealTime>
      <IsWriteable>true</IsWriteable>
      <IsReadable>true</IsReadable>
      <Ranges>
      </Ranges>
    </Reg>
    <Reg Name="Spi_Receive_Buf9">
      <Address>0x0719</Address>
      <RegVal>0x00000000</RegVal>
      <IsRealTime>true</IsRealTime>
      <IsWriteable>true</IsWriteable>
      <IsReadable>true</IsReadable>
      <Ranges>
      </Ranges>
    </Reg>
    <Reg Name="Spi_Receive_Bufa">
      <Address>0x071a</Address>
      <RegVal>0x00000000</RegVal>
      <IsRealTime>true</IsRealTime>
      <IsWriteable>true</IsWriteable>
      <IsReadable>true</IsReadable>
      <Ranges>
      </Ranges>
    </Reg>
    <Reg Name="Spi_Receive_Bufb">
      <Address>0x071b</Address>
      <RegVal>0x00000000</RegVal>
      <IsRealTime>true</IsRealTime>
      <IsWriteable>true</IsWriteable>
      <IsReadable>true</IsReadable>
      <Ranges>
      </Ranges>
    </Reg>
    <Reg Name="Spi_Receive_Bufc">
      <Address>0x071c</Address>
      <RegVal>0x00000000</RegVal>
      <IsRealTime>true</IsRealTime>
      <IsWriteable>true</IsWriteable>
      <IsReadable>true</IsReadable>
      <Ranges>
      </Ranges>
    </Reg>
    <Reg Name="Spi_Receive_Bufd">
      <Address>0x071d</Address>
      <RegVal>0x00000000</RegVal>
      <IsRealTime>true</IsRealTime>
      <IsWriteable>true</IsWriteable>
      <IsReadable>true</IsReadable>
      <Ranges>
      </Ranges>
    </Reg>
    <Reg Name="Spi_Receive_Bufe">
      <Address>0x071e</Address>
      <RegVal>0x00000000</RegVal>
      <IsRealTime>true</IsRealTime>
      <IsWriteable>true</IsWriteable>
      <IsReadable>true</IsReadable>
      <Ranges>
      </Ranges>
    </Reg>
    <Reg Name="Spi_Receive_Buff">
      <Address>0x071f</Address>
      <RegVal>0x00000000</RegVal>
      <IsRealTime>true</IsRealTime>
      <IsWriteable>true</IsWriteable>
      <IsReadable>true</IsReadable>
      <Ranges>
      </Ranges>
    </Reg>
    <Reg Name="Spi_Go">
      <Address>0x0720</Address>
      <RegVal>0x00000000</RegVal>
      <IsRealTime>true</IsRealTime>
      <IsWriteable>true</IsWriteable>
      <IsReadable>true</IsReadable>
      <Ranges>
      </Ranges>
    </Reg>
    <Reg Name="Spi_Ctrl">
      <Address>0x0721</Address>
      <RegVal>0x0000000f</RegVal>
      <IsRealTime>true</IsRealTime>
      <IsWriteable>true</IsWriteable>
      <IsReadable>true</IsReadable>
      <Ranges>
        <Range>
          <Start>10</Start>
          <End>31</End>
          <Min>0</Min>
          <Max>0</Max>
        </Range>
        <Range>
          <Start>7</Start>
          <End>7</End>
          <Min>0</Min>
          <Max>0</Max>
        </Range>
      </Ranges>
    </Reg>
    <Reg Name="Spi_Channel0_Ctrl1">
      <Address>0x0722</Address>
      <RegVal>0x00000000</RegVal>
      <IsRealTime>true</IsRealTime>
      <IsWriteable>true</IsWriteable>
      <IsReadable>true</IsReadable>
      <Ranges>
        <Range>
          <Start>6</Start>
          <End>7</End>
          <Min>0</Min>
          <Max>0</Max>
        </Range>
        <Range>
          <Start>14</Start>
          <End>15</End>
          <Min>0</Min>
          <Max>0</Max>
        </Range>
        <Range>
          <Start>22</Start>
          <End>31</End>
          <Min>0</Min>
          <Max>0</Max>
        </Range>
      </Ranges>
    </Reg>
    <Reg Name="Spi_Channel1_Ctrl1">
      <Address>0x0723</Address>
      <RegVal>0x00000000</RegVal>
      <IsRealTime>true</IsRealTime>
      <IsWriteable>true</IsWriteable>
      <IsReadable>true</IsReadable>
      <Ranges>
        <Range>
          <Start>6</Start>
          <End>7</End>
          <Min>0</Min>
          <Max>0</Max>
        </Range>
        <Range>
          <Start>14</Start>
          <End>15</End>
          <Min>0</Min>
          <Max>0</Max>
        </Range>
        <Range>
          <Start>22</Start>
          <End>31</End>
          <Min>0</Min>
          <Max>0</Max>
        </Range>
      </Ranges>
    </Reg>
    <Reg Name="Spi_Channel2_Ctrl1">
      <Address>0x0724</Address>
      <RegVal>0x00000000</RegVal>
      <IsRealTime>true</IsRealTime>
      <IsWriteable>true</IsWriteable>
      <IsReadable>true</IsReadable>
      <Ranges>
        <Range>
          <Start>6</Start>
          <End>15</End>
          <Min>0</Min>
          <Max>0</Max>
        </Range>
        <Range>
          <Start>22</Start>
          <End>31</End>
          <Min>0</Min>
          <Max>0</Max>
        </Range>
      </Ranges>
    </Reg>
    <Reg Name="Spi_Channel0_Ctrl2">
      <Address>0x0725</Address>
      <RegVal>0x00000000</RegVal>
      <IsRealTime>true</IsRealTime>
      <IsWriteable>true</IsWriteable>
      <IsReadable>true</IsReadable>
      <Ranges>
        <Range>
          <Start>2</Start>
          <End>7</End>
          <Min>0</Min>
          <Max>0</Max>
        </Range>
        <Range>
          <Start>14</Start>
          <End>15</End>
          <Min>0</Min>
          <Max>0</Max>
        </Range>
        <Range>
          <Start>22</Start>
          <End>23</End>
          <Min>0</Min>
          <Max>0</Max>
        </Range>
      </Ranges>
    </Reg>
    <Reg Name="Spi_Channel1_Ctrl2">
      <Address>0x0726</Address>
      <RegVal>0x00000000</RegVal>
      <IsRealTime>true</IsRealTime>
      <IsWriteable>true</IsWriteable>
      <IsReadable>true</IsReadable>
      <Ranges>
        <Range>
          <Start>2</Start>
          <End>7</End>
          <Min>0</Min>
          <Max>0</Max>
        </Range>
        <Range>
          <Start>14</Start>
          <End>15</End>
          <Min>0</Min>
          <Max>0</Max>
        </Range>
        <Range>
          <Start>22</Start>
          <End>23</End>
          <Min>0</Min>
          <Max>0</Max>
        </Range>
      </Ranges>
    </Reg>
    <Reg Name="Spi_Channel2_Ctrl2">
      <Address>0x0727</Address>
      <RegVal>0x00000000</RegVal>
      <IsRealTime>true</IsRealTime>
      <IsWriteable>true</IsWriteable>
      <IsReadable>true</IsReadable>
      <Ranges>
        <Range>
          <Start>8</Start>
          <End>23</End>
          <Min>0</Min>
          <Max>0</Max>
        </Range>
      </Ranges>
    </Reg>
    <Reg Name="Spi_Sync_Trigger_Del_Channel0">
      <Address>0x0728</Address>
      <RegVal>0x00000000</RegVal>
      <IsRealTime>true</IsRealTime>
      <IsWriteable>true</IsWriteable>
      <IsReadable>true</IsReadable>
      <Ranges>
      </Ranges>
    </Reg>
    <Reg Name="Spi_Sync_Trigger_Del_Channel1">
      <Address>0x0729</Address>
      <RegVal>0x00000000</RegVal>
      <IsRealTime>true</IsRealTime>
      <IsWriteable>true</IsWriteable>
      <IsReadable>true</IsReadable>
      <Ranges>
      </Ranges>
    </Reg>
    <Reg Name="Spi_Sync_Trigger_Del_Channel2">
      <Address>0x072a</Address>
      <RegVal>0x00000000</RegVal>
      <IsRealTime>true</IsRealTime>
      <IsWriteable>true</IsWriteable>
      <IsReadable>true</IsReadable>
      <Ranges>
      </Ranges>
    </Reg>
    <Reg Name="Spi_Timing_Ctrl">
      <Address>0x072b</Address>
      <RegVal>0x13271313</RegVal>
      <IsRealTime>true</IsRealTime>
      <IsWriteable>true</IsWriteable>
      <IsReadable>true</IsReadable>
      <Ranges>
      </Ranges>
    </Reg>
  </SPI>
  <Analog>
    <Reg Name="Glb_Status">
      <Address>0x0c00</Address>
      <RegVal>0x00002610</RegVal>
      <IsRealTime>true</IsRealTime>
      <IsWriteable>false</IsWriteable>
      <IsReadable>true</IsReadable>
      <Ranges>
        <Range>
          <Start>19</Start>
          <End>19</End>
          <Min>0</Min>
          <Max>0</Max>
        </Range>
        <Range>
          <Start>22</Start>
          <End>31</End>
          <Min>0</Min>
          <Max>0</Max>
        </Range>
      </Ranges>
    </Reg>
    <Reg Name="Pmu_Cfg">
      <Address>0x0c01</Address>
      <RegVal>0x00000017</RegVal>
      <IsRealTime>true</IsRealTime>
      <IsWriteable>true</IsWriteable>
      <IsReadable>true</IsReadable>
      <Ranges>
        <Range>
          <Start>7</Start>
          <End>31</End>
          <Min>0</Min>
          <Max>0</Max>
        </Range>
      </Ranges>
    </Reg>
    <Reg Name="Pll_Cfg0">
      <Address>0x0c02</Address>
      <RegVal>0x00011900</RegVal>
      <IsRealTime>true</IsRealTime>
      <IsWriteable>true</IsWriteable>
      <IsReadable>true</IsReadable>
      <Ranges>
        <Range>
          <Start>15</Start>
          <End>15</End>
          <Min>0</Min>
          <Max>0</Max>
        </Range>
        <Range>
          <Start>18</Start>
          <End>31</End>
          <Min>0</Min>
          <Max>0</Max>
        </Range>
      </Ranges>
    </Reg>
    <Reg Name="Pll_Cfg1">
      <Address>0x0c03</Address>
      <RegVal>0x02710034</RegVal>
      <IsRealTime>true</IsRealTime>
      <IsWriteable>true</IsWriteable>
      <IsReadable>true</IsReadable>
      <Ranges>
        <Range>
          <Start>7</Start>
          <End>15</End>
          <Min>0</Min>
          <Max>0</Max>
        </Range>
        <Range>
          <Start>28</Start>
          <End>30</End>
          <Min>0</Min>
          <Max>0</Max>
        </Range>
      </Ranges>
    </Reg>
    <Reg Name="Dll_Cfg0">
      <Address>0x0c04</Address>
      <RegVal>0x00000000</RegVal>
      <IsRealTime>true</IsRealTime>
      <IsWriteable>true</IsWriteable>
      <IsReadable>true</IsReadable>
      <Ranges>
        <Range>
          <Start>2</Start>
          <End>31</End>
          <Min>0</Min>
          <Max>0</Max>
        </Range>
      </Ranges>
    </Reg>
    <Reg Name="Tsensor_Cfg_Reg0">
      <Address>0x0c06</Address>
      <RegVal>0x00640803</RegVal>
      <IsRealTime>true</IsRealTime>
      <IsWriteable>true</IsWriteable>
      <IsReadable>true</IsReadable>
      <Ranges>
        <Range>
          <Start>26</Start>
          <End>31</End>
          <Min>0</Min>
          <Max>0</Max>
        </Range>
      </Ranges>
    </Reg>
    <Reg Name="Adc_Cfg">
      <Address>0x0c07</Address>
      <RegVal>0x0000008a</RegVal>
      <IsRealTime>true</IsRealTime>
      <IsWriteable>true</IsWriteable>
      <IsReadable>true</IsReadable>
      <Ranges>
        <Range>
          <Start>5</Start>
          <End>5</End>
          <Min>0</Min>
          <Max>0</Max>
        </Range>
        <Range>
          <Start>10</Start>
          <End>11</End>
          <Min>0</Min>
          <Max>0</Max>
        </Range>
        <Range>
          <Start>13</Start>
          <End>15</End>
          <Min>0</Min>
          <Max>0</Max>
        </Range>
        <Range>
          <Start>22</Start>
          <End>23</End>
          <Min>0</Min>
          <Max>0</Max>
        </Range>
        <Range>
          <Start>28</Start>
          <End>31</End>
          <Min>0</Min>
          <Max>0</Max>
        </Range>
      </Ranges>
    </Reg>
    <Reg Name="Testbuffer_Cfg">
      <Address>0x0c20</Address>
      <RegVal>0x00000000</RegVal>
      <IsRealTime>true</IsRealTime>
      <IsWriteable>true</IsWriteable>
      <IsReadable>true</IsReadable>
      <Ranges>
      </Ranges>
    </Reg>
    <Reg Name="Standby">
      <Address>0x0c28</Address>
      <RegVal>0x00000001</RegVal>
      <IsRealTime>true</IsRealTime>
      <IsWriteable>true</IsWriteable>
      <IsReadable>true</IsReadable>
      <Ranges>
        <Range>
          <Start>1</Start>
          <End>31</End>
          <Min>0</Min>
          <Max>0</Max>
        </Range>
      </Ranges>
    </Reg>
    <Reg Name="Sw_Standby">
      <Address>0x0c29</Address>
      <RegVal>0x00000000</RegVal>
      <IsRealTime>true</IsRealTime>
      <IsWriteable>true</IsWriteable>
      <IsReadable>true</IsReadable>
      <Ranges>
        <Range>
          <Start>1</Start>
          <End>31</End>
          <Min>0</Min>
          <Max>0</Max>
        </Range>
      </Ranges>
    </Reg>
    <Reg Name="Standby_Ctrl0">
      <Address>0x0c30</Address>
      <RegVal>0x00c800c0</RegVal>
      <IsRealTime>true</IsRealTime>
      <IsWriteable>true</IsWriteable>
      <IsReadable>true</IsReadable>
      <Ranges>
        <Range>
          <Start>4</Start>
          <End>5</End>
          <Min>0</Min>
          <Max>0</Max>
        </Range>
        <Range>
          <Start>8</Start>
          <End>15</End>
          <Min>0</Min>
          <Max>0</Max>
        </Range>
      </Ranges>
    </Reg>
    <Reg Name="Standby_Ctrl1">
      <Address>0x0c31</Address>
      <RegVal>0x00c800c8</RegVal>
      <IsRealTime>true</IsRealTime>
      <IsWriteable>true</IsWriteable>
      <IsReadable>true</IsReadable>
      <Ranges>
      </Ranges>
    </Reg>
    <Reg Name="I2c_Ctrl">
      <Address>0x0c32</Address>
      <RegVal>0x00003600</RegVal>
      <IsRealTime>true</IsRealTime>
      <IsWriteable>true</IsWriteable>
      <IsReadable>true</IsReadable>
      <Ranges>
        <Range>
          <Start>2</Start>
          <End>7</End>
          <Min>0</Min>
          <Max>0</Max>
        </Range>
        <Range>
          <Start>15</Start>
          <End>31</End>
          <Min>0</Min>
          <Max>0</Max>
        </Range>
      </Ranges>
    </Reg>
  </Analog>
  <MIPIDig>
    <Reg Name="Mipi_Version">
      <Address>0x0200</Address>
      <RegVal>0x00000001</RegVal>
      <IsRealTime>true</IsRealTime>
      <IsWriteable>false</IsWriteable>
      <IsReadable>true</IsReadable>
      <Ranges>
        <Range>
          <Start>8</Start>
          <End>31</End>
          <Min>0</Min>
          <Max>0</Max>
        </Range>
      </Ranges>
    </Reg>
    <Reg Name="Reset_Cycle">
      <Address>0x0204</Address>
      <RegVal>0x0000007f</RegVal>
      <IsRealTime>true</IsRealTime>
      <IsWriteable>true</IsWriteable>
      <IsReadable>true</IsReadable>
      <Ranges>
        <Range>
          <Start>8</Start>
          <End>31</End>
          <Min>0</Min>
          <Max>0</Max>
        </Range>
      </Ranges>
    </Reg>
    <Reg Name="Reset">
      <Address>0x0208</Address>
      <RegVal>0x00000000</RegVal>
      <IsRealTime>true</IsRealTime>
      <IsWriteable>true</IsWriteable>
      <IsReadable>false</IsReadable>
      <Ranges>
        <Range>
          <Start>1</Start>
          <End>31</End>
          <Min>0</Min>
          <Max>0</Max>
        </Range>
      </Ranges>
    </Reg>
    <Reg Name="Shutd_Txmcro">
      <Address>0x020c</Address>
      <RegVal>0x00000000</RegVal>
      <IsRealTime>true</IsRealTime>
      <IsWriteable>true</IsWriteable>
      <IsReadable>true</IsReadable>
      <Ranges>
        <Range>
          <Start>3</Start>
          <End>31</End>
          <Min>0</Min>
          <Max>0</Max>
        </Range>
      </Ranges>
    </Reg>
    <Reg Name="Glb_Cfg">
      <Address>0x0210</Address>
      <RegVal>0x00003015</RegVal>
      <IsRealTime>true</IsRealTime>
      <IsWriteable>true</IsWriteable>
      <IsReadable>true</IsReadable>
      <Ranges>
        <Range>
          <Start>3</Start>
          <End>3</End>
          <Min>0</Min>
          <Max>0</Max>
        </Range>
        <Range>
          <Start>7</Start>
          <End>7</End>
          <Min>0</Min>
          <Max>0</Max>
        </Range>
        <Range>
          <Start>10</Start>
          <End>11</End>
          <Min>0</Min>
          <Max>0</Max>
        </Range>
        <Range>
          <Start>14</Start>
          <End>31</End>
          <Min>0</Min>
          <Max>0</Max>
        </Range>
      </Ranges>
    </Reg>
    <Reg Name="Ulps_Cfg">
      <Address>0x0220</Address>
      <RegVal>0x00000000</RegVal>
      <IsRealTime>true</IsRealTime>
      <IsWriteable>true</IsWriteable>
      <IsReadable>true</IsReadable>
      <Ranges>
        <Range>
          <Start>4</Start>
          <End>31</End>
          <Min>0</Min>
          <Max>0</Max>
        </Range>
      </Ranges>
    </Reg>
    <Reg Name="Init_Cfg">
      <Address>0x0224</Address>
      <RegVal>0x00000000</RegVal>
      <IsRealTime>true</IsRealTime>
      <IsWriteable>true</IsWriteable>
      <IsReadable>true</IsReadable>
      <Ranges>
        <Range>
          <Start>2</Start>
          <End>31</End>
          <Min>0</Min>
          <Max>0</Max>
        </Range>
      </Ranges>
    </Reg>
    <Reg Name="Clne_Cfg">
      <Address>0x0228</Address>
      <RegVal>0x00000000</RegVal>
      <IsRealTime>true</IsRealTime>
      <IsWriteable>true</IsWriteable>
      <IsReadable>true</IsReadable>
      <Ranges>
        <Range>
          <Start>4</Start>
          <End>31</End>
          <Min>0</Min>
          <Max>0</Max>
        </Range>
      </Ranges>
    </Reg>
    <Reg Name="Ipg_Enable">
      <Address>0x0230</Address>
      <RegVal>0x00000000</RegVal>
      <IsRealTime>true</IsRealTime>
      <IsWriteable>true</IsWriteable>
      <IsReadable>true</IsReadable>
      <Ranges>
        <Range>
          <Start>3</Start>
          <End>7</End>
          <Min>0</Min>
          <Max>0</Max>
        </Range>
      </Ranges>
    </Reg>
    <Reg Name="Ipg_Cfg1">
      <Address>0x0234</Address>
      <RegVal>0x00008010</RegVal>
      <IsRealTime>true</IsRealTime>
      <IsWriteable>true</IsWriteable>
      <IsReadable>true</IsReadable>
      <Ranges>
        <Range>
          <Start>30</Start>
          <End>31</End>
          <Min>0</Min>
          <Max>0</Max>
        </Range>
      </Ranges>
    </Reg>
    <Reg Name="Ipg_Cfg2">
      <Address>0x0238</Address>
      <RegVal>0x014000f0</RegVal>
      <IsRealTime>true</IsRealTime>
      <IsWriteable>true</IsWriteable>
      <IsReadable>true</IsReadable>
      <Ranges>
        <Range>
          <Start>30</Start>
          <End>31</End>
          <Min>0</Min>
          <Max>0</Max>
        </Range>
      </Ranges>
    </Reg>
    <Reg Name="Ipg_Cfg3">
      <Address>0x023c</Address>
      <RegVal>0x00000000</RegVal>
      <IsRealTime>true</IsRealTime>
      <IsWriteable>true</IsWriteable>
      <IsReadable>true</IsReadable>
      <Ranges>
        <Range>
          <Start>0</Start>
          <End>15</End>
          <Min>0</Min>
          <Max>0</Max>
        </Range>
      </Ranges>
    </Reg>
    <Reg Name="Mipi_Status">
      <Address>0x0240</Address>
      <RegVal>0x00000000</RegVal>
      <IsRealTime>true</IsRealTime>
      <IsWriteable>false</IsWriteable>
      <IsReadable>true</IsReadable>
      <Ranges>
        <Range>
          <Start>5</Start>
          <End>7</End>
          <Min>0</Min>
          <Max>0</Max>
        </Range>
        <Range>
          <Start>13</Start>
          <End>15</End>
          <Min>0</Min>
          <Max>0</Max>
        </Range>
        <Range>
          <Start>21</Start>
          <End>23</End>
          <Min>0</Min>
          <Max>0</Max>
        </Range>
        <Range>
          <Start>25</Start>
          <End>31</End>
          <Min>0</Min>
          <Max>0</Max>
        </Range>
      </Ranges>
    </Reg>
    <Reg Name="Mipi_Error">
      <Address>0x0244</Address>
      <RegVal>0x00000000</RegVal>
      <IsRealTime>true</IsRealTime>
      <IsWriteable>false</IsWriteable>
      <IsReadable>true</IsReadable>
      <Ranges>
        <Range>
          <Start>25</Start>
          <End>31</End>
          <Min>0</Min>
          <Max>0</Max>
        </Range>
      </Ranges>
    </Reg>
    <Reg Name="Tclk_Post_Cfg">
      <Address>0x0250</Address>
      <RegVal>0x0000000f</RegVal>
      <IsRealTime>true</IsRealTime>
      <IsWriteable>true</IsWriteable>
      <IsReadable>true</IsReadable>
      <Ranges>
        <Range>
          <Start>8</Start>
          <End>31</End>
          <Min>0</Min>
          <Max>0</Max>
        </Range>
      </Ranges>
    </Reg>
    <Reg Name="Tclk_Pre_Cfg">
      <Address>0x0254</Address>
      <RegVal>0x00000001</RegVal>
      <IsRealTime>true</IsRealTime>
      <IsWriteable>true</IsWriteable>
      <IsReadable>true</IsReadable>
      <Ranges>
        <Range>
          <Start>8</Start>
          <End>31</End>
          <Min>0</Min>
          <Max>0</Max>
        </Range>
      </Ranges>
    </Reg>
    <Reg Name="Tclk_Prepare_Cfg">
      <Address>0x0258</Address>
      <RegVal>0x00000007</RegVal>
      <IsRealTime>true</IsRealTime>
      <IsWriteable>true</IsWriteable>
      <IsReadable>true</IsReadable>
      <Ranges>
        <Range>
          <Start>8</Start>
          <End>31</End>
          <Min>0</Min>
          <Max>0</Max>
        </Range>
      </Ranges>
    </Reg>
    <Reg Name="Tclk_Trail_Cfg">
      <Address>0x025c</Address>
      <RegVal>0x00000008</RegVal>
      <IsRealTime>true</IsRealTime>
      <IsWriteable>true</IsWriteable>
      <IsReadable>true</IsReadable>
      <Ranges>
        <Range>
          <Start>8</Start>
          <End>31</End>
          <Min>0</Min>
          <Max>0</Max>
        </Range>
      </Ranges>
    </Reg>
    <Reg Name="Tclk_Zero_Cfg">
      <Address>0x0260</Address>
      <RegVal>0x0000001f</RegVal>
      <IsRealTime>true</IsRealTime>
      <IsWriteable>true</IsWriteable>
      <IsReadable>true</IsReadable>
      <Ranges>
        <Range>
          <Start>8</Start>
          <End>31</End>
          <Min>0</Min>
          <Max>0</Max>
        </Range>
      </Ranges>
    </Reg>
    <Reg Name="Hs_Exit_Cfg">
      <Address>0x0264</Address>
      <RegVal>0x0000000f</RegVal>
      <IsRealTime>true</IsRealTime>
      <IsWriteable>true</IsWriteable>
      <IsReadable>true</IsReadable>
      <Ranges>
        <Range>
          <Start>8</Start>
          <End>31</End>
          <Min>0</Min>
          <Max>0</Max>
        </Range>
      </Ranges>
    </Reg>
    <Reg Name="Hs_Prepare_Cfg">
      <Address>0x0268</Address>
      <RegVal>0x00000007</RegVal>
      <IsRealTime>true</IsRealTime>
      <IsWriteable>true</IsWriteable>
      <IsReadable>true</IsReadable>
      <Ranges>
        <Range>
          <Start>8</Start>
          <End>31</End>
          <Min>0</Min>
          <Max>0</Max>
        </Range>
      </Ranges>
    </Reg>
    <Reg Name="Hs_Zero_Cfg">
      <Address>0x026c</Address>
      <RegVal>0x0000000f</RegVal>
      <IsRealTime>true</IsRealTime>
      <IsWriteable>true</IsWriteable>
      <IsReadable>true</IsReadable>
      <Ranges>
        <Range>
          <Start>8</Start>
          <End>31</End>
          <Min>0</Min>
          <Max>0</Max>
        </Range>
      </Ranges>
    </Reg>
    <Reg Name="Hs_Trail_Cfg">
      <Address>0x0270</Address>
      <RegVal>0x00000008</RegVal>
      <IsRealTime>true</IsRealTime>
      <IsWriteable>true</IsWriteable>
      <IsReadable>true</IsReadable>
      <Ranges>
        <Range>
          <Start>8</Start>
          <End>31</End>
          <Min>0</Min>
          <Max>0</Max>
        </Range>
      </Ranges>
    </Reg>
    <Reg Name="T_Init_Cfg">
      <Address>0x0274</Address>
      <RegVal>0x0000003f</RegVal>
      <IsRealTime>true</IsRealTime>
      <IsWriteable>true</IsWriteable>
      <IsReadable>true</IsReadable>
      <Ranges>
        <Range>
          <Start>8</Start>
          <End>31</End>
          <Min>0</Min>
          <Max>0</Max>
        </Range>
      </Ranges>
    </Reg>
    <Reg Name="T_Ipx_Cfg">
      <Address>0x0278</Address>
      <RegVal>0x00000007</RegVal>
      <IsRealTime>true</IsRealTime>
      <IsWriteable>true</IsWriteable>
      <IsReadable>true</IsReadable>
      <Ranges>
        <Range>
          <Start>8</Start>
          <End>31</End>
          <Min>0</Min>
          <Max>0</Max>
        </Range>
      </Ranges>
    </Reg>
    <Reg Name="T_Wakeup_Cfg">
      <Address>0x027c</Address>
      <RegVal>0x0000003f</RegVal>
      <IsRealTime>true</IsRealTime>
      <IsWriteable>true</IsWriteable>
      <IsReadable>true</IsReadable>
      <Ranges>
        <Range>
          <Start>8</Start>
          <End>31</End>
          <Min>0</Min>
          <Max>0</Max>
        </Range>
      </Ranges>
    </Reg>
    <Reg Name="Hs_Wakeup_Cfg">
      <Address>0x0280</Address>
      <RegVal>0x00000000</RegVal>
      <IsRealTime>true</IsRealTime>
      <IsWriteable>true</IsWriteable>
      <IsReadable>true</IsReadable>
      <Ranges>
        <Range>
          <Start>8</Start>
          <End>31</End>
          <Min>0</Min>
          <Max>0</Max>
        </Range>
      </Ranges>
    </Reg>
    <Reg Name="Sd_En_Cfg">
      <Address>0x0288</Address>
      <RegVal>0x00000000</RegVal>
      <IsRealTime>true</IsRealTime>
      <IsWriteable>true</IsWriteable>
      <IsReadable>true</IsReadable>
      <Ranges>
        <Range>
          <Start>8</Start>
          <End>31</End>
          <Min>0</Min>
          <Max>0</Max>
        </Range>
      </Ranges>
    </Reg>
    <Reg Name="Ulps_En_Cfg">
      <Address>0x028c</Address>
      <RegVal>0x00000000</RegVal>
      <IsRealTime>true</IsRealTime>
      <IsWriteable>true</IsWriteable>
      <IsReadable>true</IsReadable>
      <Ranges>
        <Range>
          <Start>8</Start>
          <End>31</End>
          <Min>0</Min>
          <Max>0</Max>
        </Range>
      </Ranges>
    </Reg>
  </MIPIDig>
  <MIPIAna>
    <Reg Name="Obs_Cfg">
      <Address>0x0a90</Address>
      <RegVal>0x00000001</RegVal>
      <IsRealTime>true</IsRealTime>
      <IsWriteable>true</IsWriteable>
      <IsReadable>true</IsReadable>
      <Ranges>
        <Range>
          <Start>3</Start>
          <End>31</End>
          <Min>0</Min>
          <Max>0</Max>
        </Range>
      </Ranges>
    </Reg>
    <Reg Name="Clk_Isel_Cfg">
      <Address>0x0a98</Address>
      <RegVal>0x00001111</RegVal>
      <IsRealTime>true</IsRealTime>
      <IsWriteable>true</IsWriteable>
      <IsReadable>true</IsReadable>
      <Ranges>
        <Range>
          <Start>2</Start>
          <End>3</End>
          <Min>0</Min>
          <Max>0</Max>
        </Range>
        <Range>
          <Start>5</Start>
          <End>7</End>
          <Min>0</Min>
          <Max>0</Max>
        </Range>
        <Range>
          <Start>10</Start>
          <End>11</End>
          <Min>0</Min>
          <Max>0</Max>
        </Range>
        <Range>
          <Start>14</Start>
          <End>31</End>
          <Min>0</Min>
          <Max>0</Max>
        </Range>
      </Ranges>
    </Reg>
    <Reg Name="Data_Isel_Cfg">
      <Address>0x0a9c</Address>
      <RegVal>0x00001111</RegVal>
      <IsRealTime>true</IsRealTime>
      <IsWriteable>true</IsWriteable>
      <IsReadable>true</IsReadable>
      <Ranges>
        <Range>
          <Start>2</Start>
          <End>3</End>
          <Min>0</Min>
          <Max>0</Max>
        </Range>
        <Range>
          <Start>6</Start>
          <End>7</End>
          <Min>0</Min>
          <Max>0</Max>
        </Range>
        <Range>
          <Start>10</Start>
          <End>11</End>
          <Min>0</Min>
          <Max>0</Max>
        </Range>
        <Range>
          <Start>14</Start>
          <End>31</End>
          <Min>0</Min>
          <Max>0</Max>
        </Range>
      </Ranges>
    </Reg>
    <Reg Name="Is_Legsel_Cfg">
      <Address>0x0ab4</Address>
      <RegVal>0x00000101</RegVal>
      <IsRealTime>true</IsRealTime>
      <IsWriteable>true</IsWriteable>
      <IsReadable>true</IsReadable>
      <Ranges>
        <Range>
          <Start>2</Start>
          <End>7</End>
          <Min>0</Min>
          <Max>0</Max>
        </Range>
        <Range>
          <Start>10</Start>
          <End>31</End>
          <Min>0</Min>
          <Max>0</Max>
        </Range>
      </Ranges>
    </Reg>
    <Reg Name="Is_En_Cfg">
      <Address>0x0ab8</Address>
      <RegVal>0x00000007</RegVal>
      <IsRealTime>true</IsRealTime>
      <IsWriteable>true</IsWriteable>
      <IsReadable>true</IsReadable>
      <Ranges>
        <Range>
          <Start>3</Start>
          <End>31</End>
          <Min>0</Min>
          <Max>0</Max>
        </Range>
      </Ranges>
    </Reg>
  </MIPIAna>
  <Efuse>
    <Reg Name="Fuse_Wr_Reg0">
      <Address>0x0f00</Address>
      <RegVal>0x00000000</RegVal>
      <IsRealTime>true</IsRealTime>
      <IsWriteable>true</IsWriteable>
      <IsReadable>true</IsReadable>
      <Ranges>
        <Range>
          <Start>11</Start>
          <End>11</End>
          <Min>0</Min>
          <Max>0</Max>
        </Range>
        <Range>
          <Start>22</Start>
          <End>31</End>
          <Min>0</Min>
          <Max>0</Max>
        </Range>
      </Ranges>
    </Reg>
    <Reg Name="Fuse_Wr_Reg1">
      <Address>0x0f01</Address>
      <RegVal>0x00000000</RegVal>
      <IsRealTime>true</IsRealTime>
      <IsWriteable>true</IsWriteable>
      <IsReadable>true</IsReadable>
      <Ranges>
      </Ranges>
    </Reg>
    <Reg Name="Fuse_Wr_Reg2">
      <Address>0x0f02</Address>
      <RegVal>0x00000000</RegVal>
      <IsRealTime>true</IsRealTime>
      <IsWriteable>true</IsWriteable>
      <IsReadable>true</IsReadable>
      <Ranges>
        <Range>
          <Start>13</Start>
          <End>15</End>
          <Min>0</Min>
          <Max>0</Max>
        </Range>
        <Range>
          <Start>21</Start>
          <End>31</End>
          <Min>0</Min>
          <Max>0</Max>
        </Range>
      </Ranges>
    </Reg>
    <Reg Name="Fuse_Wr_Reg3">
      <Address>0x0f03</Address>
      <RegVal>0x00000000</RegVal>
      <IsRealTime>true</IsRealTime>
      <IsWriteable>true</IsWriteable>
      <IsReadable>true</IsReadable>
      <Ranges>
      </Ranges>
    </Reg>
    <Reg Name="Fuse_Wr_Reg4">
      <Address>0x0f04</Address>
      <RegVal>0x00000000</RegVal>
      <IsRealTime>true</IsRealTime>
      <IsWriteable>true</IsWriteable>
      <IsReadable>true</IsReadable>
      <Ranges>
      </Ranges>
    </Reg>
    <Reg Name="Fuse_Wr_Reg5">
      <Address>0x0f05</Address>
      <RegVal>0x00000000</RegVal>
      <IsRealTime>true</IsRealTime>
      <IsWriteable>true</IsWriteable>
      <IsReadable>true</IsReadable>
      <Ranges>
      </Ranges>
    </Reg>
    <Reg Name="Fuse_Wr_Reg6">
      <Address>0x0f06</Address>
      <RegVal>0x00000000</RegVal>
      <IsRealTime>true</IsRealTime>
      <IsWriteable>true</IsWriteable>
      <IsReadable>true</IsReadable>
      <Ranges>
      </Ranges>
    </Reg>
    <Reg Name="Fuse_Wr_Reg7">
      <Address>0x0f07</Address>
      <RegVal>0x00000000</RegVal>
      <IsRealTime>true</IsRealTime>
      <IsWriteable>true</IsWriteable>
      <IsReadable>true</IsReadable>
      <Ranges>
      </Ranges>
    </Reg>
    <Reg Name="Fuse_Wr_Reg8">
      <Address>0x0f08</Address>
      <RegVal>0x00000000</RegVal>
      <IsRealTime>true</IsRealTime>
      <IsWriteable>true</IsWriteable>
      <IsReadable>true</IsReadable>
      <Ranges>
      </Ranges>
    </Reg>
    <Reg Name="Fuse_Wr_Reg9">
      <Address>0x0f09</Address>
      <RegVal>0x00000000</RegVal>
      <IsRealTime>true</IsRealTime>
      <IsWriteable>true</IsWriteable>
      <IsReadable>true</IsReadable>
      <Ranges>
      </Ranges>
    </Reg>
    <Reg Name="Fuse_Wr_Rega">
      <Address>0x0f0a</Address>
      <RegVal>0x00000000</RegVal>
      <IsRealTime>true</IsRealTime>
      <IsWriteable>true</IsWriteable>
      <IsReadable>true</IsReadable>
      <Ranges>
      </Ranges>
    </Reg>
    <Reg Name="Fuse_Wr_Regb">
      <Address>0x0f0b</Address>
      <RegVal>0x00000000</RegVal>
      <IsRealTime>true</IsRealTime>
      <IsWriteable>true</IsWriteable>
      <IsReadable>true</IsReadable>
      <Ranges>
      </Ranges>
    </Reg>
    <Reg Name="Fuse_Wr_Regc">
      <Address>0x0f0c</Address>
      <RegVal>0x00000000</RegVal>
      <IsRealTime>true</IsRealTime>
      <IsWriteable>true</IsWriteable>
      <IsReadable>true</IsReadable>
      <Ranges>
      </Ranges>
    </Reg>
    <Reg Name="Fuse_Wr_Regd">
      <Address>0x0f0d</Address>
      <RegVal>0x00000000</RegVal>
      <IsRealTime>true</IsRealTime>
      <IsWriteable>true</IsWriteable>
      <IsReadable>true</IsReadable>
      <Ranges>
      </Ranges>
    </Reg>
    <Reg Name="Fuse_Wr_Rege">
      <Address>0x0f0e</Address>
      <RegVal>0x00000000</RegVal>
      <IsRealTime>true</IsRealTime>
      <IsWriteable>true</IsWriteable>
      <IsReadable>true</IsReadable>
      <Ranges>
      </Ranges>
    </Reg>
    <Reg Name="Fuse_Wr_Regf">
      <Address>0x0f0f</Address>
      <RegVal>0x00000000</RegVal>
      <IsRealTime>true</IsRealTime>
      <IsWriteable>true</IsWriteable>
      <IsReadable>true</IsReadable>
      <Ranges>
      </Ranges>
    </Reg>
    <Reg Name="Fuse_Rd_Reg0">
      <Address>0x0f10</Address>
      <RegVal>0x00000000</RegVal>
      <IsRealTime>true</IsRealTime>
      <IsWriteable>true</IsWriteable>
      <IsReadable>true</IsReadable>
      <Ranges>
      </Ranges>
    </Reg>
    <Reg Name="Fuse_Rd_Reg1">
      <Address>0x0f11</Address>
      <RegVal>0x00000000</RegVal>
      <IsRealTime>true</IsRealTime>
      <IsWriteable>true</IsWriteable>
      <IsReadable>true</IsReadable>
      <Ranges>
      </Ranges>
    </Reg>
    <Reg Name="Fuse_Rd_Reg2">
      <Address>0x0f12</Address>
      <RegVal>0x00000000</RegVal>
      <IsRealTime>true</IsRealTime>
      <IsWriteable>true</IsWriteable>
      <IsReadable>true</IsReadable>
      <Ranges>
      </Ranges>
    </Reg>
    <Reg Name="Fuse_Rd_Reg3">
      <Address>0x0f13</Address>
      <RegVal>0x00000000</RegVal>
      <IsRealTime>true</IsRealTime>
      <IsWriteable>true</IsWriteable>
      <IsReadable>true</IsReadable>
      <Ranges>
      </Ranges>
    </Reg>
    <Reg Name="Fuse_Rd_Reg4">
      <Address>0x0f14</Address>
      <RegVal>0x00000000</RegVal>
      <IsRealTime>true</IsRealTime>
      <IsWriteable>true</IsWriteable>
      <IsReadable>true</IsReadable>
      <Ranges>
      </Ranges>
    </Reg>
    <Reg Name="Fuse_Rd_Reg5">
      <Address>0x0f15</Address>
      <RegVal>0x00000000</RegVal>
      <IsRealTime>true</IsRealTime>
      <IsWriteable>true</IsWriteable>
      <IsReadable>true</IsReadable>
      <Ranges>
      </Ranges>
    </Reg>
    <Reg Name="Fuse_Rd_Reg6">
      <Address>0x0f16</Address>
      <RegVal>0x00000000</RegVal>
      <IsRealTime>true</IsRealTime>
      <IsWriteable>true</IsWriteable>
      <IsReadable>true</IsReadable>
      <Ranges>
      </Ranges>
    </Reg>
    <Reg Name="Fuse_Rd_Reg7">
      <Address>0x0f17</Address>
      <RegVal>0x00000000</RegVal>
      <IsRealTime>true</IsRealTime>
      <IsWriteable>true</IsWriteable>
      <IsReadable>true</IsReadable>
      <Ranges>
      </Ranges>
    </Reg>
    <Reg Name="Fuse_Rd_Reg8">
      <Address>0x0f18</Address>
      <RegVal>0x00000000</RegVal>
      <IsRealTime>true</IsRealTime>
      <IsWriteable>true</IsWriteable>
      <IsReadable>true</IsReadable>
      <Ranges>
      </Ranges>
    </Reg>
    <Reg Name="Fuse_Rd_Reg9">
      <Address>0x0f19</Address>
      <RegVal>0x00000000</RegVal>
      <IsRealTime>true</IsRealTime>
      <IsWriteable>true</IsWriteable>
      <IsReadable>true</IsReadable>
      <Ranges>
      </Ranges>
    </Reg>
    <Reg Name="Fuse_Rd_Rega">
      <Address>0x0f1a</Address>
      <RegVal>0x00000000</RegVal>
      <IsRealTime>true</IsRealTime>
      <IsWriteable>true</IsWriteable>
      <IsReadable>true</IsReadable>
      <Ranges>
      </Ranges>
    </Reg>
    <Reg Name="Fuse_Rd_Regb">
      <Address>0x0f1b</Address>
      <RegVal>0x00000000</RegVal>
      <IsRealTime>true</IsRealTime>
      <IsWriteable>true</IsWriteable>
      <IsReadable>true</IsReadable>
      <Ranges>
      </Ranges>
    </Reg>
    <Reg Name="Fuse_Rd_Regc">
      <Address>0x0f1c</Address>
      <RegVal>0x00000000</RegVal>
      <IsRealTime>true</IsRealTime>
      <IsWriteable>true</IsWriteable>
      <IsReadable>true</IsReadable>
      <Ranges>
      </Ranges>
    </Reg>
    <Reg Name="Fuse_Rd_Regd">
      <Address>0x0f1d</Address>
      <RegVal>0x00000000</RegVal>
      <IsRealTime>true</IsRealTime>
      <IsWriteable>true</IsWriteable>
      <IsReadable>true</IsReadable>
      <Ranges>
      </Ranges>
    </Reg>
    <Reg Name="Fuse_Rd_Rege">
      <Address>0x0f1e</Address>
      <RegVal>0x00000000</RegVal>
      <IsRealTime>true</IsRealTime>
      <IsWriteable>true</IsWriteable>
      <IsReadable>true</IsReadable>
      <Ranges>
      </Ranges>
    </Reg>
    <Reg Name="Fuse_Rd_Regf">
      <Address>0x0f1f</Address>
      <RegVal>0x00000000</RegVal>
      <IsRealTime>true</IsRealTime>
      <IsWriteable>true</IsWriteable>
      <IsReadable>true</IsReadable>
      <Ranges>
      </Ranges>
    </Reg>
    <Reg Name="Burst_Op_Ctrl">
      <Address>0x0f80</Address>
      <RegVal>0x00000000</RegVal>
      <IsRealTime>true</IsRealTime>
      <IsWriteable>true</IsWriteable>
      <IsReadable>true</IsReadable>
      <Ranges>
        <Range>
          <Start>16</Start>
          <End>29</End>
          <Min>0</Min>
          <Max>0</Max>
        </Range>
      </Ranges>
    </Reg>
    <Reg Name="Fuse_Rd_Param">
      <Address>0x0f81</Address>
      <RegVal>0x00108426</RegVal>
      <IsRealTime>true</IsRealTime>
      <IsWriteable>true</IsWriteable>
      <IsReadable>true</IsReadable>
      <Ranges>
        <Range>
          <Start>25</Start>
          <End>31</End>
          <Min>0</Min>
          <Max>0</Max>
        </Range>
      </Ranges>
    </Reg>
    <Reg Name="Fuse_Wr_Param0">
      <Address>0x0f82</Address>
      <RegVal>0x01320046</RegVal>
      <IsRealTime>true</IsRealTime>
      <IsWriteable>true</IsWriteable>
      <IsReadable>true</IsReadable>
      <Ranges>
        <Range>
          <Start>29</Start>
          <End>31</End>
          <Min>0</Min>
          <Max>0</Max>
        </Range>
      </Ranges>
    </Reg>
    <Reg Name="Fuse_Wr_Param1">
      <Address>0x0f83</Address>
      <RegVal>0x00000001</RegVal>
      <IsRealTime>true</IsRealTime>
      <IsWriteable>true</IsWriteable>
      <IsReadable>true</IsReadable>
      <Ranges>
        <Range>
          <Start>10</Start>
          <End>31</End>
          <Min>0</Min>
          <Max>0</Max>
        </Range>
      </Ranges>
    </Reg>
    <Reg Name="Single_Wr_Ctrl">
      <Address>0x0f84</Address>
      <RegVal>0x000000000</RegVal>
      <IsRealTime>true</IsRealTime>
      <IsWriteable>true</IsWriteable>
      <IsReadable>true</IsReadable>
      <Ranges>
        <Range>
          <Start>14</Start>
          <End>29</End>
          <Min>0</Min>
          <Max>0</Max>
        </Range>
      </Ranges>
    </Reg>
    <Reg Name="Single_Rd_Ctrl">
      <Address>0x0f85</Address>
      <RegVal>0x000000000</RegVal>
      <IsRealTime>true</IsRealTime>
      <IsWriteable>true</IsWriteable>
      <IsReadable>true</IsReadable>
      <Ranges>
        <Range>
          <Start>14</Start>
          <End>29</End>
          <Min>0</Min>
          <Max>0</Max>
        </Range>
      </Ranges>
    </Reg>
    <Reg Name="Fuse_Status">
      <Address>0x0f88</Address>
      <RegVal>0x000000000</RegVal>
      <IsRealTime>true</IsRealTime>
      <IsWriteable>false</IsWriteable>
      <IsReadable>true</IsReadable>
      <Ranges>
        <Range>
          <Start>2</Start>
          <End>7</End>
          <Min>0</Min>
          <Max>0</Max>
        </Range>
        <Range>
          <Start>12</Start>
          <End>15</End>
          <Min>0</Min>
          <Max>0</Max>
        </Range>
        <Range>
          <Start>23</Start>
          <End>23</End>
          <Min>0</Min>
          <Max>0</Max>
        </Range>
      </Ranges>
    </Reg>
    <Reg Name="Fuse_Cfgen">
      <Address>0x0f90</Address>
      <RegVal>0x000000000</RegVal>
      <IsRealTime>true</IsRealTime>
      <IsWriteable>true</IsWriteable>
      <IsReadable>true</IsReadable>
      <Ranges>
        <Range>
          <Start>18</Start>
          <End>31</End>
          <Min>0</Min>
          <Max>0</Max>
        </Range>
      </Ranges>
    </Reg>
    <Reg Name="Fuse_Cfgval0">
      <Address>0x0f91</Address>
      <RegVal>0x00099490</RegVal>
      <IsRealTime>true</IsRealTime>
      <IsWriteable>true</IsWriteable>
      <IsReadable>true</IsReadable>
      <Ranges>
        <Range>
          <Start>11</Start>
          <End>11</End>
          <Min>0</Min>
          <Max>0</Max>
        </Range>
        <Range>
          <Start>22</Start>
          <End>31</End>
          <Min>0</Min>
          <Max>0</Max>
        </Range>
      </Ranges>
    </Reg>
    <Reg Name="Fuse_Cfgval1">
      <Address>0x0f92</Address>
      <RegVal>0x88888888</RegVal>
      <IsRealTime>true</IsRealTime>
      <IsWriteable>true</IsWriteable>
      <IsReadable>true</IsReadable>
      <Ranges>
      </Ranges>
    </Reg>
    <Reg Name="Fuse_Cfgval2">
      <Address>0x0f93</Address>
      <RegVal>0x00000000</RegVal>
      <IsRealTime>true</IsRealTime>
      <IsWriteable>true</IsWriteable>
      <IsReadable>true</IsReadable>
      <Ranges>
        <Range>
          <Start>13</Start>
          <End>15</End>
          <Min>0</Min>
          <Max>0</Max>
        </Range>
        <Range>
          <Start>21</Start>
          <End>31</End>
          <Min>0</Min>
          <Max>0</Max>
        </Range>
      </Ranges>
    </Reg>
  </Efuse>
  <VDriver>
    <Reg Name="Unknown">
      <Address>0x00</Address>
      <RegVal>0x00000000</RegVal>
      <IsRealTime>true</IsRealTime>
      <IsWriteable>true</IsWriteable>
      <IsReadable>true</IsReadable>
      <Ranges>
        <Range>
          <Start>5</Start>
          <End>6</End>
          <Min>0</Min>
          <Max>0</Max>
        </Range>
        <Range>
          <Start>8</Start>
          <End>31</End>
          <Min>0</Min>
          <Max>0</Max>
        </Range>
      </Ranges>
    </Reg>
    <Reg Name="IBIAS_APCL1">
      <Address>0x01</Address>
      <RegVal>0x00000000</RegVal>
      <IsRealTime>true</IsRealTime>
      <IsWriteable>true</IsWriteable>
      <IsReadable>true</IsReadable>
      <Ranges>
        <Range>
          <Start>8</Start>
          <End>31</End>
          <Min>0</Min>
          <Max>0</Max>
        </Range>
      </Ranges>
    </Reg>
    <Reg Name="IBIAS_APCH1">
      <Address>0x02</Address>
      <RegVal>0x00000000</RegVal>
      <IsRealTime>true</IsRealTime>
      <IsWriteable>true</IsWriteable>
      <IsReadable>true</IsReadable>
      <Ranges>
        <Range>
          <Start>8</Start>
          <End>31</End>
          <Min>0</Min>
          <Max>0</Max>
        </Range>
      </Ranges>
    </Reg>
    <Reg Name="ISW_APCL1">
      <Address>0x03</Address>
      <RegVal>0x00000000</RegVal>
      <IsRealTime>true</IsRealTime>
      <IsWriteable>true</IsWriteable>
      <IsReadable>true</IsReadable>
      <Ranges>
        <Range>
          <Start>8</Start>
          <End>31</End>
          <Min>0</Min>
          <Max>0</Max>
        </Range>
      </Ranges>
    </Reg>
    <Reg Name="ISW_APCH1">
      <Address>0x04</Address>
      <RegVal>0x00000000</RegVal>
      <IsRealTime>true</IsRealTime>
      <IsWriteable>true</IsWriteable>
      <IsReadable>true</IsReadable>
      <Ranges>
        <Range>
          <Start>8</Start>
          <End>31</End>
          <Min>0</Min>
          <Max>0</Max>
        </Range>
      </Ranges>
    </Reg>
    <Reg Name="ISW_APCL2">
      <Address>0x05</Address>
      <RegVal>0x00000000</RegVal>
      <IsRealTime>true</IsRealTime>
      <IsWriteable>true</IsWriteable>
      <IsReadable>true</IsReadable>
      <Ranges>
        <Range>
          <Start>8</Start>
          <End>31</End>
          <Min>0</Min>
          <Max>0</Max>
        </Range>
      </Ranges>
    </Reg>
    <Reg Name="ISW_APCH2">
      <Address>0x06</Address>
      <RegVal>0x00000000</RegVal>
      <IsRealTime>true</IsRealTime>
      <IsWriteable>true</IsWriteable>
      <IsReadable>true</IsReadable>
      <Ranges>
        <Range>
          <Start>8</Start>
          <End>31</End>
          <Min>0</Min>
          <Max>0</Max>
        </Range>
      </Ranges>
    </Reg>
    <Reg Name="IBIAS_FIX">
      <Address>0x07</Address>
      <RegVal>0x00000000</RegVal>
      <IsRealTime>true</IsRealTime>
      <IsWriteable>true</IsWriteable>
      <IsReadable>true</IsReadable>
      <Ranges>
        <Range>
          <Start>8</Start>
          <End>31</End>
          <Min>0</Min>
          <Max>0</Max>
        </Range>
      </Ranges>
    </Reg>
    <Reg Name="ISW_FIX">
      <Address>0x08</Address>
      <RegVal>0x00000000</RegVal>
      <IsRealTime>true</IsRealTime>
      <IsWriteable>true</IsWriteable>
      <IsReadable>true</IsReadable>
      <Ranges>
        <Range>
          <Start>8</Start>
          <End>31</End>
          <Min>0</Min>
          <Max>0</Max>
        </Range>
      </Ranges>
    </Reg>
    <Reg Name="IBIAS_BACK">
      <Address>0x09</Address>
      <RegVal>0x00000000</RegVal>
      <IsRealTime>true</IsRealTime>
      <IsWriteable>true</IsWriteable>
      <IsReadable>true</IsReadable>
      <Ranges>
        <Range>
          <Start>8</Start>
          <End>31</End>
          <Min>0</Min>
          <Max>0</Max>
        </Range>
      </Ranges>
    </Reg>
    <Reg Name="Unknown">
      <Address>0x0A</Address>
      <RegVal>0x00000000</RegVal>
      <IsRealTime>true</IsRealTime>
      <IsWriteable>true</IsWriteable>
      <IsReadable>true</IsReadable>
      <Ranges>
        <Range>
          <Start>8</Start>
          <End>31</End>
          <Min>0</Min>
          <Max>0</Max>
        </Range>
      </Ranges>
    </Reg>
    <Reg Name="PD_TARGET_IN">
      <Address>0x0B</Address>
      <RegVal>0x00000000</RegVal>
      <IsRealTime>true</IsRealTime>
      <IsWriteable>true</IsWriteable>
      <IsReadable>true</IsReadable>
      <Ranges>
        <Range>
          <Start>8</Start>
          <End>31</End>
          <Min>0</Min>
          <Max>0</Max>
        </Range>
      </Ranges>
    </Reg>
    <Reg Name="TEMP_INITIAL_IN">
      <Address>0x0C</Address>
      <RegVal>0x00000000</RegVal>
      <IsRealTime>true</IsRealTime>
      <IsWriteable>true</IsWriteable>
      <IsReadable>true</IsReadable>
      <Ranges>
        <Range>
          <Start>8</Start>
          <End>31</End>
          <Min>0</Min>
          <Max>0</Max>
        </Range>
      </Ranges>
    </Reg>
    <Reg Name="Unknown">
      <Address>0x0D</Address>
      <RegVal>0x00000000</RegVal>
      <IsRealTime>true</IsRealTime>
      <IsWriteable>true</IsWriteable>
      <IsReadable>true</IsReadable>
      <Ranges>
        <Range>
          <Start>8</Start>
          <End>31</End>
          <Min>0</Min>
          <Max>0</Max>
        </Range>
      </Ranges>
    </Reg>
    <Reg Name="Unknown">
      <Address>0x0E</Address>
      <RegVal>0x00000000</RegVal>
      <IsRealTime>true</IsRealTime>
      <IsWriteable>true</IsWriteable>
      <IsReadable>true</IsReadable>
      <Ranges>
        <Range>
          <Start>8</Start>
          <End>31</End>
          <Min>0</Min>
          <Max>0</Max>
        </Range>
      </Ranges>
    </Reg>
    <Reg Name="Unknown">
      <Address>0x0F</Address>
      <RegVal>0x00000000</RegVal>
      <IsRealTime>true</IsRealTime>
      <IsWriteable>true</IsWriteable>
      <IsReadable>true</IsReadable>
      <Ranges>
        <Range>
          <Start>8</Start>
          <End>31</End>
          <Min>0</Min>
          <Max>0</Max>
        </Range>
      </Ranges>
    </Reg>
    <Reg Name="Unknown">
      <Address>0x10</Address>
      <RegVal>0x00000000</RegVal>
      <IsRealTime>true</IsRealTime>
      <IsWriteable>true</IsWriteable>
      <IsReadable>true</IsReadable>
      <Ranges>
        <Range>
          <Start>8</Start>
          <End>31</End>
          <Min>0</Min>
          <Max>0</Max>
        </Range>
      </Ranges>
    </Reg>
    <Reg Name="Unknown">
      <Address>0x11</Address>
      <RegVal>0x00000000</RegVal>
      <IsRealTime>true</IsRealTime>
      <IsWriteable>true</IsWriteable>
      <IsReadable>true</IsReadable>
      <Ranges>
        <Range>
          <Start>8</Start>
          <End>31</End>
          <Min>0</Min>
          <Max>0</Max>
        </Range>
      </Ranges>
    </Reg>
    <Reg Name="Unknown">
      <Address>0x12</Address>
      <RegVal>0x00000000</RegVal>
      <IsRealTime>true</IsRealTime>
      <IsWriteable>true</IsWriteable>
      <IsReadable>true</IsReadable>
      <Ranges>
        <Range>
          <Start>8</Start>
          <End>31</End>
          <Min>0</Min>
          <Max>0</Max>
        </Range>
      </Ranges>
    </Reg>
    <Reg Name="Unknown">
      <Address>0x13</Address>
      <RegVal>0x00000000</RegVal>
      <IsRealTime>true</IsRealTime>
      <IsWriteable>true</IsWriteable>
      <IsReadable>true</IsReadable>
      <Ranges>
        <Range>
          <Start>8</Start>
          <End>31</End>
          <Min>0</Min>
          <Max>0</Max>
        </Range>
      </Ranges>
    </Reg>
    <Reg Name="Ver16">
      <Address>0x23</Address>
      <RegVal>0x00000000</RegVal>
      <IsRealTime>true</IsRealTime>
      <IsWriteable>false</IsWriteable>
      <IsReadable>true</IsReadable>
      <Ranges>
        <Range>
          <Start>8</Start>
          <End>31</End>
          <Min>0</Min>
          <Max>0</Max>
        </Range>
      </Ranges>
    </Reg>
    <Reg Name="ErrorMonitor">
      <Address>0x24</Address>
      <RegVal>0x00000000</RegVal>
      <IsRealTime>true</IsRealTime>
      <IsWriteable>false</IsWriteable>
      <IsReadable>true</IsReadable>
      <Ranges>
        <Range>
          <Start>8</Start>
          <End>31</End>
          <Min>0</Min>
          <Max>0</Max>
        </Range>
      </Ranges>
    </Reg>
    <Reg Name="GL_RST">
      <Address>0x25</Address>
      <RegVal>0x00000000</RegVal>
      <IsRealTime>true</IsRealTime>
      <IsWriteable>true</IsWriteable>
      <IsReadable>true</IsReadable>
      <Ranges>
        <Range>
          <Start>8</Start>
          <End>31</End>
          <Min>0</Min>
          <Max>0</Max>
        </Range>
      </Ranges>
    </Reg>
    <Reg Name="INTERNAL_PD_RES">
      <Address>0x26</Address>
      <RegVal>0x00000000</RegVal>
      <IsRealTime>true</IsRealTime>
      <IsWriteable>true</IsWriteable>
      <IsReadable>true</IsReadable>
      <Ranges>
        <Range>
          <Start>8</Start>
          <End>31</End>
          <Min>0</Min>
          <Max>0</Max>
        </Range>
      </Ranges>
    </Reg>
    <Reg Name="Unknown">
      <Address>0x27</Address>
      <RegVal>0x00000000</RegVal>
      <IsRealTime>true</IsRealTime>
      <IsWriteable>true</IsWriteable>
      <IsReadable>true</IsReadable>
      <Ranges>
        <Range>
          <Start>8</Start>
          <End>31</End>
          <Min>0</Min>
          <Max>0</Max>
        </Range>
      </Ranges>
    </Reg>
    <Reg Name="RIPPLE_CONTROL_FALL">
      <Address>0x28</Address>
      <RegVal>0x00000000</RegVal>
      <IsRealTime>true</IsRealTime>
      <IsWriteable>true</IsWriteable>
      <IsReadable>true</IsReadable>
      <Ranges>
        <Range>
          <Start>8</Start>
          <End>31</End>
          <Min>0</Min>
          <Max>0</Max>
        </Range>
      </Ranges>
    </Reg>
    <Reg Name="Ver26">
      <Address>0x29</Address>
      <RegVal>0x00000000</RegVal>
      <IsRealTime>true</IsRealTime>
      <IsWriteable>false</IsWriteable>
      <IsReadable>true</IsReadable>
      <Ranges>
        <Range>
          <Start>8</Start>
          <End>31</End>
          <Min>0</Min>
          <Max>0</Max>
        </Range>
      </Ranges>
    </Reg>
    <Reg Name="DIF_ERR_UPPER_THRES">
      <Address>0x2B</Address>
      <RegVal>0x00000000</RegVal>
      <IsRealTime>true</IsRealTime>
      <IsWriteable>false</IsWriteable>
      <IsReadable>true</IsReadable>
      <Ranges>
        <Range>
          <Start>8</Start>
          <End>31</End>
          <Min>0</Min>
          <Max>0</Max>
        </Range>
      </Ranges>
    </Reg>
    <Reg Name="DIF_ERR_LOWER_THRES">
      <Address>0x2C</Address>
      <RegVal>0x00000000</RegVal>
      <IsRealTime>true</IsRealTime>
      <IsWriteable>false</IsWriteable>
      <IsReadable>true</IsReadable>
      <Ranges>
        <Range>
          <Start>8</Start>
          <End>31</End>
          <Min>0</Min>
          <Max>0</Max>
        </Range>
      </Ranges>
    </Reg>
    <Reg Name="Unknown">
      <Address>0x2D</Address>
      <RegVal>0x00000000</RegVal>
      <IsRealTime>true</IsRealTime>
      <IsWriteable>true</IsWriteable>
      <IsReadable>true</IsReadable>
      <Ranges>
        <Range>
          <Start>8</Start>
          <End>31</End>
          <Min>0</Min>
          <Max>0</Max>
        </Range>
      </Ranges>
    </Reg>
    <Reg Name="Unknown">
      <Address>0x2E</Address>
      <RegVal>0x00000000</RegVal>
      <IsRealTime>true</IsRealTime>
      <IsWriteable>true</IsWriteable>
      <IsReadable>true</IsReadable>
      <Ranges>
        <Range>
          <Start>8</Start>
          <End>31</End>
          <Min>0</Min>
          <Max>0</Max>
        </Range>
      </Ranges>
    </Reg>
    <Reg Name="Unknown">
      <Address>0x2F</Address>
      <RegVal>0x00000000</RegVal>
      <IsRealTime>true</IsRealTime>
      <IsWriteable>true</IsWriteable>
      <IsReadable>true</IsReadable>
      <Ranges>
        <Range>
          <Start>8</Start>
          <End>31</End>
          <Min>0</Min>
          <Max>0</Max>
        </Range>
      </Ranges>
    </Reg>
    <Reg Name="DUTY_CYCLE_INCREASE">
      <Address>0x30</Address>
      <RegVal>0x00000000</RegVal>
      <IsRealTime>true</IsRealTime>
      <IsWriteable>true</IsWriteable>
      <IsReadable>true</IsReadable>
      <Ranges>
        <Range>
          <Start>8</Start>
          <End>31</End>
          <Min>0</Min>
          <Max>0</Max>
        </Range>
      </Ranges>
    </Reg>
    <Reg Name="DUTY_CYCLE_DECREASE">
      <Address>0x31</Address>
      <RegVal>0x00000000</RegVal>
      <IsRealTime>true</IsRealTime>
      <IsWriteable>true</IsWriteable>
      <IsReadable>true</IsReadable>
      <Ranges>
        <Range>
          <Start>8</Start>
          <End>31</End>
          <Min>0</Min>
          <Max>0</Max>
        </Range>
      </Ranges>
    </Reg>
    <Reg Name="FALL_EDGE_CONTROL">
      <Address>0x32</Address>
      <RegVal>0x00000000</RegVal>
      <IsRealTime>true</IsRealTime>
      <IsWriteable>true</IsWriteable>
      <IsReadable>true</IsReadable>
      <Ranges>
        <Range>
          <Start>8</Start>
          <End>31</End>
          <Min>0</Min>
          <Max>0</Max>
        </Range>
      </Ranges>
    </Reg>
  </VDriver>
</RegMap>